LICENSE
MANIFEST.in
README.md
setup.cfg
setup.py
mapentity/VERSION
mapentity/__init__.py
mapentity/apps.py
mapentity/context_processors.py
mapentity/decorators.py
mapentity/filters.py
mapentity/forms.py
mapentity/helpers.py
mapentity/middleware.py
mapentity/models.py
mapentity/pagination.py
mapentity/registry.py
mapentity/renderers.py
mapentity/settings.py
mapentity/tokens.py
mapentity/urls.py
mapentity/utils.py
mapentity/widgets.py
mapentity.egg-info/PKG-INFO
mapentity.egg-info/SOURCES.txt
mapentity.egg-info/dependency_links.txt
mapentity.egg-info/not-zip-safe
mapentity.egg-info/requires.txt
mapentity.egg-info/top_level.txt
mapentity/locale/de/LC_MESSAGES/django.mo
mapentity/locale/de/LC_MESSAGES/django.po
mapentity/locale/de/LC_MESSAGES/djangojs.mo
mapentity/locale/de/LC_MESSAGES/djangojs.po
mapentity/locale/en/LC_MESSAGES/django.mo
mapentity/locale/en/LC_MESSAGES/django.po
mapentity/locale/en/LC_MESSAGES/djangojs.mo
mapentity/locale/en/LC_MESSAGES/djangojs.po
mapentity/locale/es/LC_MESSAGES/django.mo
mapentity/locale/es/LC_MESSAGES/django.po
mapentity/locale/es/LC_MESSAGES/djangojs.mo
mapentity/locale/es/LC_MESSAGES/djangojs.po
mapentity/locale/fr/LC_MESSAGES/django.mo
mapentity/locale/fr/LC_MESSAGES/django.po
mapentity/locale/fr/LC_MESSAGES/djangojs.mo
mapentity/locale/fr/LC_MESSAGES/djangojs.po
mapentity/locale/nl/LC_MESSAGES/django.mo
mapentity/locale/nl/LC_MESSAGES/django.po
mapentity/locale/nl/LC_MESSAGES/djangojs.mo
mapentity/locale/nl/LC_MESSAGES/djangojs.po
mapentity/management/__init__.py
mapentity/management/commands/__init__.py
mapentity/management/commands/update_permissions_mapentity.py
mapentity/migrations/0001_initial.py
mapentity/migrations/0002_alter_logentry_options.py
mapentity/migrations/__init__.py
mapentity/serializers/__init__.py
mapentity/serializers/commasv.py
mapentity/serializers/datatables.py
mapentity/serializers/fields.py
mapentity/serializers/geojson.py
mapentity/serializers/gpx.py
mapentity/serializers/helpers.py
mapentity/serializers/shapefile.py
mapentity/static/images/logo-header.png
mapentity/static/images/logo-login.png
mapentity/static/mapentity/RelatedObjectLookups.js
mapentity/static/mapentity/jquery.deserialize.js
