Metadata-Version: 2.4
Name: mapentity
Version: 8.16.1
Summary: Generic CRUD with maps for django
Home-page: https://github.com/makinacorpus/django-mapentity
Download-URL: https://pypi.python.org/pypi/mapentity/
Author: Makina Corpus
Author-email: geobi@makina-corpus.com
License: BSD, see LICENSE file.
Classifier: Topic :: Utilities
Classifier: Natural Language :: English
Classifier: Operating System :: OS Independent
Classifier: Intended Audience :: Developers
Classifier: Environment :: Web Environment
Classifier: Framework :: Django
Classifier: Development Status :: 5 - Production/Stable
Classifier: Programming Language :: Python :: 3
Requires-Python: >=3.9
License-File: LICENSE
Requires-Dist: BeautifulSoup4
Requires-Dist: cairocffi
Requires-Dist: Django
Requires-Dist: tzdata
Requires-Dist: django-appypod
Requires-Dist: django-compressor
Requires-Dist: django-crispy-forms>=2.0
Requires-Dist: crispy-bootstrap4
Requires-Dist: django-embed-video
Requires-Dist: django-filter
Requires-Dist: django-leaflet<0.20,>=0.19
Requires-Dist: django-modeltranslation
Requires-Dist: django-tinymce>=3
Requires-Dist: django-weasyprint
Requires-Dist: djangorestframework
Requires-Dist: djangorestframework-gis
Requires-Dist: djangorestframework-datatables
Requires-Dist: easy-thumbnails
Requires-Dist: fiona
Requires-Dist: gpxpy
Requires-Dist: lxml
Requires-Dist: paperclip
Requires-Dist: requests
Requires-Dist: weasyprint
Provides-Extra: dev
Requires-Dist: django-debug-toolbar; extra == "dev"
Requires-Dist: ruff; extra == "dev"
Requires-Dist: freezegun; extra == "dev"
Requires-Dist: factory_boy; extra == "dev"
Requires-Dist: coverage; extra == "dev"
Requires-Dist: tblib; extra == "dev"
Dynamic: author
Dynamic: author-email
Dynamic: classifier
Dynamic: description
Dynamic: download-url
Dynamic: home-page
Dynamic: license
Dynamic: license-file
Dynamic: provides-extra
Dynamic: requires-dist
Dynamic: requires-python
Dynamic: summary
